blette/__init__.py
blette/version.py
blette/apis/__init__.py
blette/apis/blette_inferencer.py
blette/apis/inference.py
blette/apis/utils.py
blette/datasets/__init__.py
blette/datasets/base_edge_dataset.py
blette/datasets/bdd100k.py
blette/datasets/bsds500.py
blette/datasets/cityscapes.py
blette/datasets/sbd.py
blette/datasets/synthia_cityscapes.py
blette/datasets/transforms/__init__.py
blette/datasets/transforms/corruptions.py
blette/datasets/transforms/formatting.py
blette/datasets/transforms/generate_edge.py
blette/datasets/transforms/loading.py
blette/datasets/transforms/transforms.py
blette/engine/__init__.py
blette/engine/hooks/__init__.py
blette/engine/hooks/visualization_hook.py
blette/engine/optimizers/__init__.py
blette/evaluation/__init__.py
blette/evaluation/edge_eval_helpers/__init__.py
blette/evaluation/edge_eval_helpers/bdd100k.py
blette/evaluation/edge_eval_helpers/synthia_cityscapes.py
blette/evaluation/metrics/__init__.py
blette/evaluation/metrics/fscore.py
blette/models/__init__.py
blette/models/data_preprocessor.py
blette/models/backbones/__init__.py
blette/models/backbones/cbam_resnet.py
blette/models/backbones/convnext.py
blette/models/backbones/densenet.py
blette/models/backbones/hrformer.py
blette/models/backbones/hrnet.py
blette/models/backbones/mtan_resnet.py
blette/models/backbones/pidinet_backbone.py
blette/models/backbones/resnest.py
blette/models/backbones/resnet.py
blette/models/backbones/vgg.py
blette/models/decode_heads/__init__.py
blette/models/decode_heads/base_decode_head.py
blette/models/decode_heads/casenet_head.py
blette/models/decode_heads/dds_head.py
blette/models/decode_heads/dff_head.py
blette/models/decode_heads/hed_head.py
blette/models/decode_heads/pidinet_head.py
blette/models/decode_heads/rcf_head.py
blette/models/decode_heads/utils.py
blette/models/detectors/__init__.py
blette/models/detectors/base.py
blette/models/detectors/edge_tta.py
blette/models/detectors/encoder_decoder.py
blette/models/losses/__init__.py
blette-1.0.0.dist-info/LICENSE
blette-1.0.0.dist-info/METADATA
blette-1.0.0.dist-info/WHEEL
blette-1.0.0.dist-info/top_level.txt
blette-1.0.0.dist-info/RECORD
