Metadata-Version: 2.1
Name: blette
Version: 1.0.0
Summary: Edge Detection Toolbox and Benchmark
Home-page: http://github.com/haruishi43/blette
Author: Haruya Ishikawa
Author-email: 
License: Apache License 2.0
Keywords: computer vision,edge detection,semantic edge detection
Classifier: Development Status :: 4 - Beta
Classifier: Operating System :: OS Independent
Classifier: Programming Language :: Python :: 3.7
Classifier: Programming Language :: Python :: 3.8
Classifier: Programming Language :: Python :: 3.9
License-File: LICENSE
Requires-Dist: albumentations
Requires-Dist: cityscapesscripts
Requires-Dist: einops
Requires-Dist: ftfy
Requires-Dist: imagecorruptions
Requires-Dist: matplotlib
Requires-Dist: mat73
Requires-Dist: scikit-learn
Requires-Dist: scikit-image
Requires-Dist: torchmetrics
Requires-Dist: prettytable
Requires-Dist: pyEdgeEval >=0.2.7
Requires-Dist: regex
Requires-Dist: wandb
